aies_nlp_preprocessing_tk/__init__.py
aies_nlp_preprocessing_tk/dataprocessing.py
aies_nlp_preprocessing_tk/preprocessing.py
aies_nlp_preprocessing_tk-1.0.1.dist-info/METADATA
aies_nlp_preprocessing_tk-1.0.1.dist-info/WHEEL
aies_nlp_preprocessing_tk-1.0.1.dist-info/top_level.txt
aies_nlp_preprocessing_tk-1.0.1.dist-info/RECORD
